{
    "configurations": [
        {
            "browse": {
                "databaseFilename": "${default}",
                "limitSymbolsToIncludedHeaders": false
            },
            "includePath": [
                "/opt/ros/melodic/include/**",
                "/home/gen2bot/catkin_ws/src/actionlib_tutorials/include/**",
                "/home/gen2bot/catkin_ws/src/gen2bot/include/**",
                "/usr/include/**",
                "${workspaceFolder}/include/gen2bot"
            ],
            "name": "ROS",
            "intelliSenseMode": "gcc-arm64",
            "compilerPath": "/usr/bin/gcc",
            "cStandard": "gnu11",
            "cppStandard": "c++14"
        }
    ],
    "version": 4
}